Metadata-Version: 1.0
Name: bonc-vertica
Version: 1.5.6
Summary: 操作vertica的小工具
Home-page: UNKNOWN
Author: 陈忠润
Author-email: chenzhongrun@bonc.com.cn
License: UNKNOWN
Platform: UNKNOWN
